fifeforspark/__init__.py
fifeforspark/__main__.py
fifeforspark/base_modelers.py
fifeforspark/gbt_modelers.py
fifeforspark/lgb_modelers.py
fifeforspark/processors.py
fifeforspark/rf_modelers.py
fifeforspark/utils.py
fifeforspark-0.0.2.dist-info/LICENSE.txt
fifeforspark-0.0.2.dist-info/METADATA
fifeforspark-0.0.2.dist-info/WHEEL
fifeforspark-0.0.2.dist-info/entry_points.txt
fifeforspark-0.0.2.dist-info/top_level.txt
fifeforspark-0.0.2.dist-info/RECORD
