Metadata-Version: 2.1
Name: fifeforspark
Version: 0.0.2
Summary: Finite-Interval Forecasting Engine for Spark: Machine learning models for discrete-time survival analysis and multivariate time series forecasting for Apache Spark
Home-page: https://github.com/IDA-HumanCapital/fife_for_spark
Author: Institute for Defense Analyses
Author-email: humancapital@ida.org
License: AGPLv3+
Platform: UNKNOWN
Classifier: Development Status :: 4 - Beta
Classifier: Intended Audience :: Science/Research
Classifier: License :: OSI Approved :: GNU Affero General Public License v3 or later (AGPLv3+)
Classifier: Programming Language :: Python :: 3
Classifier: Programming Language :: Python :: 3.7
Classifier: Topic :: Scientific/Engineering :: Information Analysis
License-File: LICENSE.txt
Requires-Dist: ipython
Requires-Dist: lifelines
Requires-Dist: pyspark
Requires-Dist: findspark
Requires-Dist: numpy
Requires-Dist: pandas
Requires-Dist: tqdm
